README.rst
setup.cfg
setup.py
celery_tracker.egg-info/PKG-INFO
celery_tracker.egg-info/SOURCES.txt
celery_tracker.egg-info/dependency_links.txt
celery_tracker.egg-info/entry_points.txt
celery_tracker.egg-info/requires.txt
celery_tracker.egg-info/top_level.txt
tracker/__init__.py
tracker/service.py
tracker/bin/__init__.py
tracker/bin/tracker.py
tracker/configs/__init__.py
tracker/configs/celeryconfig.py
tracker/management/__init__.py
tracker/management/commands/__init__.py
tracker/management/commands/tracker.py
tracker/plugins/__init__.py
tracker/plugins/base.py
tracker/plugins/fluent.py
tracker/plugins/logging.py
tracker/plugins/receive.py
tracker/plugins/web.py
tracker/plugins/zabbix.py
tracker/receivers/__init__.py
tracker/receivers/base.py
tracker/senders/__init__.py
tracker/senders/base.py
tracker/senders/fluent.py
tracker/senders/logging.py
tracker/tracking/__init__.py
tracker/tracking/state.py
tracker/tracking/storage.py
tracker/utils/__init__.py
tracker/utils/loader.py