Metadata-Version: 1.0
Name: celery-tracker
Version: 0.3.2
Summary: Receive/Sending event tracking data for the Celery
Home-page: https://github.com/ikeikeikeike/celery-tracker
Author: Tatsuo Ikeda
Author-email: jp.ne.co.jp at gmail.com
License: MIT
Keywords: django,celery,tracking,agent,metrics
Platform: UNKNOWN
Classifier: Development Status :: 4 - Beta
Classifier: Intended Audience :: Developers
Classifier: License :: OSI Approved :: BSD License
Classifier: Topic :: System :: Monitoring
Classifier: Topic :: System :: Distributed Computing
Classifier: Programming Language :: Python
Classifier: Programming Language :: Python :: 2
Classifier: Programming Language :: Python :: 2.6
Classifier: Programming Language :: Python :: 2.7
Classifier: Programming Language :: Python :: Implementation :: CPython
Classifier: Operating System :: OS Independent
